fast_edges_extraction/__init__.py
fast_edges_extraction/_extract_edges.cpython-310-darwin.so
fast_edges_extraction/_extract_edges.c
fast_edges_extraction-0.1.5.dist-info/RECORD
fast_edges_extraction-0.1.5.dist-info/WHEEL
fast_edges_extraction-0.1.5.dist-info/top_level.txt
fast_edges_extraction-0.1.5.dist-info/METADATA
fast_edges_extraction-0.1.5.dist-info/licenses/LICENSE
