Metadata-Version: 2.4
Name: fast_edges_extraction
Version: 0.1.5
Summary: Edge extraction for triangle meshes
Author: Louis Pujol
License: MIT License
Project-URL: repository, https://github.com/Louis-Pujol/fast-edges-extraction
Project-URL: changelog, https://github.com/Louis-Pujol/fast-edges-extraction/blob/main/CHANGELOG.md
Requires-Python: >=3.9
License-File: LICENSE
Requires-Dist: numpy
Dynamic: license-file
